epyfun/__init__.py
epyfun/fs.py
epyfun/pandas.py
epyfun/plotly.py
epyfun/py.typed
epyfun/web.py
epyfun-0.3.8.dist-info/LICENSE
epyfun-0.3.8.dist-info/METADATA
epyfun-0.3.8.dist-info/WHEEL
epyfun-0.3.8.dist-info/RECORD
