Metadata-Version: 2.1
Name: epyfun
Version: 0.3.8
Summary: epyfun
Home-page: https://github.com/edalfon/epyfun
License: MIT
Author: Eduardo Alfonso-Sierra
Author-email: edalfon@gmail.com
Requires-Python: >=3.9,<4.0
Classifier: Development Status :: 4 - Beta
Classifier: License :: OSI Approved :: MIT License
Classifier: Programming Language :: Python :: 3
Classifier: Programming Language :: Python :: 3.9
Classifier: Programming Language :: Python :: 3.10
Classifier: Programming Language :: Python :: 3.11
Classifier: Programming Language :: Python :: 3.12
Requires-Dist: chardet (>=5.2.0)
Requires-Dist: pandas (>=2.1.4)
Requires-Dist: pandas-stubs (>=2.2.2.240514,<3.0.0.0)
Requires-Dist: plotly (>=5.18.0)
Requires-Dist: requests (>=2.32.2,<3.0.0)
Requires-Dist: types-requests (>=2.32.0.20240523,<3.0.0.0)
Project-URL: Changelog, https://github.com/edalfon/epyfun/releases
Project-URL: Documentation, https://epyfun.readthedocs.io
Project-URL: Repository, https://github.com/edalfon/epyfun
